git_timestamp/__init__.py
git_timestamp/timestamp.py
git_timestamp-1.1.1.dist-info/LICENSE.md
git_timestamp-1.1.1.dist-info/METADATA
git_timestamp-1.1.1.dist-info/WHEEL
git_timestamp-1.1.1.dist-info/entry_points.txt
git_timestamp-1.1.1.dist-info/top_level.txt
git_timestamp-1.1.1.dist-info/RECORD
