Metadata-Version: 2.1
Name: git-timestamp
Version: 1.1.1
Summary: GIT Timestamping client for Zeitgitter
Home-page: https://zeitgitter.net
Author: Marcel Waldvogel
Author-email: marcel.waldvogel@trifence.ch
License: MIT
Classifier: Development Status :: 5 - Production/Stable
Classifier: Environment :: Console
Classifier: Intended Audience :: Information Technology
Classifier: Programming Language :: Python
Classifier: License :: OSI Approved :: MIT License
Classifier: Operating System :: OS Independent
Classifier: Natural Language :: English
Classifier: Topic :: Software Development :: Version Control :: Git
Classifier: Topic :: Security
Classifier: Topic :: Utilities
Requires-Python: >=3.4
License-File: LICENSE.md
Requires-Dist: configargparse
Requires-Dist: deltat (~=1.1)
Requires-Dist: pygit2
Requires-Dist: python-gnupg
Requires-Dist: requests
Requires-Dist: setuptools
